zeroday_sentinel-1.1.0.dist-info/licenses/LICENSE
zerodaysentinel/__init__.py
zerodaysentinel/cli.py
zeroday_sentinel-1.1.0.dist-info/METADATA
zeroday_sentinel-1.1.0.dist-info/WHEEL
zeroday_sentinel-1.1.0.dist-info/entry_points.txt
zeroday_sentinel-1.1.0.dist-info/top_level.txt
zeroday_sentinel-1.1.0.dist-info/RECORD
