Metadata-Version: 2.4
Name: zeroday-sentinel
Version: 1.1.0
Summary: CVE Fetcher
License-Expression: MIT
Requires-Python: >=3.8
License-File: LICENSE
Requires-Dist: curl_cffi
Requires-Dist: flatten_json
Requires-Dist: colorama
Requires-Dist: pandas
Requires-Dist: pyfiglet
Requires-Dist: python-dotenv
Dynamic: license-file
